{
  "name": "benbarnett/jQuery-Animate-Enhanced",
  "version": "1.1.0",
  "main": "./jquery.animate-enhanced.min.js",
  "description": "Extend $.animate() to detect CSS transitions for Webkit, Mozilla, IE>=10 and Opera and convert animations automatically.",
  "license": "MIT (http://opensource.org/licenses/mit-license.php)",
  "ignore": [
    ".jshintrc",
    "**/*.txt"
  ],
  "dependencies": {
    "jquery": ">=1.3.2"
  },
  "homepage": "https://github.com/benbarnett/jquery-animate-enhanced",
  "_release": "1.1.0",
  "_resolution": {
    "type": "version",
    "tag": "1.1.0",
    "commit": "58c60474630eed7e3ceb596ef0268cdc1974337b"
  },
  "_source": "https://github.com/benbarnett/jquery-animate-enhanced.git",
  "_target": "^1.1.0",
  "_originalSource": "benbarnett/jQuery-Animate-Enhanced=benbarnett/jquery-animate-enhanced"
}